kirami_plugin_boardgame-0.1.1.dist-info/METADATA
kirami_plugin_boardgame-0.1.1.dist-info/WHEEL
kirami_plugin_boardgame-0.1.1.dist-info/licenses/LICENSE
kirami_plugin_boardgame/__init__.py
kirami_plugin_boardgame/game.py
kirami_plugin_boardgame/go.py
kirami_plugin_boardgame/gomoku.py
kirami_plugin_boardgame/model.py
kirami_plugin_boardgame/othello.py
kirami_plugin_boardgame/svg.py
kirami_plugin_boardgame-0.1.1.dist-info/RECORD
