Metadata-Version: 2.1
Name: kirami-plugin-boardgame
Version: 0.1.1
Summary: 五子棋、围棋、黑白棋游戏
Author-Email: FrostN_0v0 <1614591760@qq.com>
License: MIT
Requires-Python: >=3.10
